jqktrader/__init__.py
jqktrader/api.py
jqktrader/clienttrader.py
jqktrader/config/__init__.py
jqktrader/config/client.py
jqktrader/exceptions.py
jqktrader/grid_strategies.py
jqktrader/log.py
jqktrader/pop_dialog_handler.py
jqktrader/refresh_strategies.py
jqktrader/utils/__init__.py
jqktrader/utils/captcha.py
jqktrader/utils/misc.py
jqktrader/utils/perf.py
jqktrader/utils/stock.py
jqktrader/utils/win_gui.py
jqktrader-0.1.4.dist-info/LICENSE
jqktrader-0.1.4.dist-info/WHEEL
jqktrader-0.1.4.dist-info/METADATA
jqktrader-0.1.4.dist-info/RECORD
