Metadata-Version: 2.1
Name: jqktrader
Version: 0.1.4
Summary: 
Author: pluto
Author-email: mayuanchi1029@gmail.com
Requires-Python: >=3.8,<3.11
Classifier: Programming Language :: Python :: 3
Classifier: Programming Language :: Python :: 3.8
Classifier: Programming Language :: Python :: 3.9
Classifier: Programming Language :: Python :: 3.10
Requires-Dist: easyutils (>=0.1.7,<0.2.0)
Requires-Dist: pandas (>=1.5.1,<2.0.0)
Requires-Dist: pypiwin32 (>=223,<224)
Requires-Dist: pytesseract (>=0.3.10,<0.4.0)
Requires-Dist: pywinauto (>=0.6.8,<0.7.0)
